common/__init__.py
common/application_resources.py
common/configuration.py
common/version.py
zoe_analytics-0.8.1.dist-info/DESCRIPTION.rst
zoe_analytics-0.8.1.dist-info/METADATA
zoe_analytics-0.8.1.dist-info/RECORD
zoe_analytics-0.8.1.dist-info/WHEEL
zoe_analytics-0.8.1.dist-info/entry_points.txt
zoe_analytics-0.8.1.dist-info/metadata.json
zoe_analytics-0.8.1.dist-info/top_level.txt
zoe_client/__init__.py
zoe_client/client.py
zoe_client/entities.py
zoe_client/entrypoint.py
zoe_client/ipc.py
zoe_scheduler/__init__.py
zoe_scheduler/emails.py
zoe_scheduler/entrypoint.py
zoe_scheduler/exceptions.py
zoe_scheduler/ipc.py
zoe_scheduler/object_storage.py
zoe_scheduler/periodic_tasks.py
zoe_scheduler/platform.py
zoe_scheduler/platform_status.py
zoe_scheduler/proxy_manager.py
zoe_scheduler/scheduler.py
zoe_scheduler/stats.py
zoe_scheduler/swarm_client.py
zoe_scheduler/urls.py
zoe_scheduler/state/__init__.py
zoe_scheduler/state/application.py
zoe_scheduler/state/cluster.py
zoe_scheduler/state/container.py
zoe_scheduler/state/execution.py
zoe_scheduler/state/proxy.py
zoe_scheduler/state/user.py
zoe_web/__init__.py
zoe_web/entrypoint.py
zoe_web/utils.py
zoe_web/api/__init__.py
zoe_web/web/__init__.py
zoe_web/web/applications.py
zoe_web/web/start.py
zoe_web/web/status.py
