Metadata-Version: 2.0
Name: zoe-analytics
Version: 0.8.1
Summary: Zoe - Analytics on demand
Home-page: https://github.com/DistributedSystemsGroup/zoe
Author: Daniele Venzano
Author-email: venza@brownhat.org
License: Apache 2.0
Keywords: spark analytics docker swarm containers notebook
Platform: UNKNOWN
Classifier: Development Status :: 3 - Alpha
Classifier: Environment :: Web Environment
Classifier: Framework :: IPython
Classifier: Intended Audience :: Developers
Classifier: Intended Audience :: Science/Research
Classifier: Topic :: Education
Classifier: Operating System :: POSIX :: Linux
Classifier: Topic :: Software Development
Classifier: Topic :: System :: Distributed Computing
Classifier: License :: OSI Approved :: Apache Software License
Classifier: Programming Language :: Python :: 3 :: Only
Classifier: Programming Language :: Python :: 3.4
Requires-Dist: Flask (>=0.10.1)
Requires-Dist: SQLAlchemy (>=1.0.8)
Requires-Dist: docker-py (>=1.3.0)
Requires-Dist: python-dateutil (>=2.4.2)
Requires-Dist: pyzmq (>=14.0.1)
Requires-Dist: tornado (>=4.2.1)
Provides-Extra: dev
Requires-Dist: Sphinx; extra == 'dev'
Provides-Extra: test
Requires-Dist: coverage; extra == 'test'
Requires-Dist: pytest; extra == 'test'
